bosbase/__init__.py
bosbase/auth.py
bosbase/client.py
bosbase/exceptions.py
bosbase/refresh.py
bosbase/types.py
bosbase/utils.py
bosbase/services/__init__.py
bosbase/services/backup.py
bosbase/services/base.py
bosbase/services/batch.py
bosbase/services/cache.py
bosbase/services/collection.py
bosbase/services/cron.py
bosbase/services/file.py
bosbase/services/graphql.py
bosbase/services/health.py
bosbase/services/langchaingo.py
bosbase/services/llm_document.py
bosbase/services/log.py
bosbase/services/plugin.py
bosbase/services/pubsub.py
bosbase/services/realtime.py
bosbase/services/record.py
bosbase/services/redis.py
bosbase/services/script.py
bosbase/services/script_permissions.py
bosbase/services/settings.py
bosbase/services/sql.py
bosbase/services/vector.py
bosbase-0.1.4.dist-info/METADATA
bosbase-0.1.4.dist-info/WHEEL
bosbase-0.1.4.dist-info/licenses/LICENSE
bosbase-0.1.4.dist-info/RECORD
