Metadata-Version: 2.4
Name: bosbase
Version: 0.1.4
Summary: Official Python SDK for interacting with the BosBase API.
Project-URL: Documentation, https://docs.bosbase.com
Project-URL: Source, https://github.com/bosbase
Author-email: BosBase <support@bosbase.com>
License: MIT
License-File: LICENSE
Classifier: License :: OSI Approved :: MIT License
Classifier: Operating System :: OS Independent
Classifier: Programming Language :: Python :: 3
Classifier: Programming Language :: Python :: 3.9
Classifier: Programming Language :: Python :: 3.10
Classifier: Programming Language :: Python :: 3.11
Classifier: Programming Language :: Python :: 3.12
Requires-Python: >=3.9
Requires-Dist: requests>=2.31.0
Requires-Dist: websocket-client>=1.8.0
